mymathutils/__init__.py
mymathutils/operations.py
edees_mathutils-0.1.0.dist-info/METADATA
edees_mathutils-0.1.0.dist-info/WHEEL
edees_mathutils-0.1.0.dist-info/top_level.txt
edees_mathutils-0.1.0.dist-info/RECORD
