Metadata-Version: 2.4
Name: edees_mathutils
Version: 0.1.0
Summary: Simple math utility functions
Author-email: Your Name <your@email.com>
Project-URL: homepage, https://github.com/yourname/mymathutils
Requires-Python: >=3.8
